certbot_extra_formats/__init__.py
certbot_extra_formats-0.1.4.dist-info/METADATA
certbot_extra_formats-0.1.4.dist-info/WHEEL
certbot_extra_formats-0.1.4.dist-info/entry_points.txt
certbot_extra_formats-0.1.4.dist-info/top_level.txt
certbot_extra_formats-0.1.4.dist-info/RECORD
