Metadata-Version: 2.1
Name: certbot-extra-formats
Version: 0.1.4
Summary: Writes a 'Let's Encrypt' certificate compatible with a given application
Home-page: https://github.com/tallero/certbot-extra-formats
Author: Pellegrino Prevete
Author-email: pellegrinoprevete@gmail.com
Classifier: Programming Language :: Python :: 3
Classifier: License :: OSI Approved :: GNU Affero General Public License v3 or later (AGPLv3+)
Classifier: Operating System :: Unix
Requires-Dist: certbot
